examples/__init__.py
examples/main.py
matplotlib_backend_qtquick/__init__.py
matplotlib_backend_qtquick/backend_qtquick.py
matplotlib_backend_qtquick/backend_qtquickagg.py
matplotlib_backend_qtquick/qt_compat.py
tests/__init__.py
tests/testBackend.py
matplotlib_backend_qtquick-0.0.8.dist-info/LICENSE
matplotlib_backend_qtquick-0.0.8.dist-info/METADATA
matplotlib_backend_qtquick-0.0.8.dist-info/WHEEL
matplotlib_backend_qtquick-0.0.8.dist-info/top_level.txt
matplotlib_backend_qtquick-0.0.8.dist-info/RECORD
