Metadata-Version: 2.1
Name: matplotlib-backend-qtquick
Version: 0.0.8
Summary: A QtQuick backend for matplotlib
Home-page: https://github.com/jmitrevs/matplotlib_backend_qtquick
Author: Jovan Mitrevski
Author-email: j.p.mitrevski@gmail.com
License: UNKNOWN
Platform: UNKNOWN
Classifier: Programming Language :: Python :: 3
Classifier: License :: OSI Approved :: MIT License
Classifier: Operating System :: OS Independent
Requires-Python: >=3.6
